[
  1,
  [
    "ecpdLyjvZBwrvm+cedCcQy",
    "1cAb1gJclM7rZYwBL4DxnW",
    "75XboP4QVGvIQhc22qdtWD",
    "3cZ2iQrddAGruSXZBRx7c4",
    "1dvkXUruVHzI4nIURDGfsV"
  ],
  [
    "node",
    "_spriteFrame",
    "_textureSetter",
    "root",
    "item",
    "layout",
    "scrollview",
    "data"
  ],
  [
    [
      "cc.Node",
      [
        "_name",
        "_components",
        "_prefab",
        "_contentSize",
        "_parent",
        "_children",
        "_trs",
        "_color",
        "_anchorPoint"
      ],
      2,
      9,
      4,
      5,
      1,
      2,
      7,
      5,
      5
    ],
    [
      "cc.Layout",
      [
        "_resize",
        "_N$layoutType",
        "_N$spacingY",
        "_N$paddingTop",
        "_N$paddingBottom",
        "_N$paddingLeft",
        "_N$paddingRight",
        "node",
        "_layoutSize"
      ],
      -4,
      1,
      5
    ],
    [
      "cc.PrefabInfo",
      [
        "fileId",
        "root",
        "asset"
      ],
      2,
      1,
      1
    ],
    [
      "b9bd9dnnsxA37tiy/eMG0Zn",
      [
        "type",
        "scaleType",
        "node"
      ],
      1,
      1
    ],
    [
      "cc.Sprite",
      [
        "_sizeMode",
        "node",
        "_materials",
        "_spriteFrame"
      ],
      2,
      1,
      3,
      6
    ],
    [
      "cc.Button",
      [
        "_N$transition",
        "node",
        "clickEvents"
      ],
      2,
      1,
      9
    ],
    [
      "cc.Label",
      [
        "_string",
        "_fontSize",
        "_N$verticalAlign",
        "_lineHeight",
        "_N$horizontalAlign",
        "_N$overflow",
        "node",
        "_materials"
      ],
      -3,
      1,
      3
    ],
    "cc.SpriteFrame",
    [
      "cc.Prefab",
      [
        "_name"
      ],
      2
    ],
    [
      "cc.Node",
      [
        "_name",
        "_parent",
        "_children",
        "_components",
        "_prefab",
        "_contentSize",
        "_anchorPoint",
        "_trs"
      ],
      2,
      1,
      2,
      12,
      4,
      5,
      5,
      7
    ],
    [
      "3cb15XGsE5GQZggPIvrXbSn",
      [
        "node",
        "scrollview",
        "layout",
        "item"
      ],
      3,
      1,
      1,
      1,
      1
    ],
    [
      "cc.BlockInputEvents",
      [
        "node"
      ],
      3,
      1
    ],
    [
      "cc.Mask",
      [
        "node",
        "_materials"
      ],
      3,
      1,
      3
    ],
    [
      "cc.Widget",
      [
        "_alignFlags",
        "_top",
        "node"
      ],
      1,
      1
    ],
    [
      "cc.ClickEvent",
      [
        "_componentId",
        "handler",
        "target"
      ],
      1,
      1
    ],
    [
      "cc.ScrollView",
      [
        "horizontal",
        "node",
        "_N$content"
      ],
      2,
      1,
      1
    ]
  ],
  [
    [
      2,
      0,
      1,
      2,
      2
    ],
    [
      0,
      0,
      4,
      5,
      1,
      2,
      3,
      6,
      2
    ],
    [
      0,
      0,
      4,
      1,
      2,
      3,
      6,
      2
    ],
    [
      0,
      0,
      4,
      1,
      2,
      7,
      3,
      2
    ],
    [
      11,
      0,
      1
    ],
    [
      3,
      1,
      2,
      2
    ],
    [
      4,
      0,
      1,
      2,
      3,
      2
    ],
    [
      6,
      0,
      1,
      3,
      4,
      2,
      6,
      7,
      6
    ],
    [
      8,
      0,
      2
    ],
    [
      0,
      0,
      5,
      1,
      2,
      3,
      2
    ],
    [
      0,
      0,
      4,
      5,
      1,
      2,
      7,
      3,
      2
    ],
    [
      0,
      0,
      4,
      5,
      1,
      2,
      3,
      8,
      2
    ],
    [
      0,
      0,
      4,
      5,
      1,
      2,
      3,
      8,
      6,
      2
    ],
    [
      9,
      0,
      1,
      2,
      3,
      4,
      5,
      6,
      7,
      2
    ],
    [
      10,
      0,
      1,
      2,
      3,
      1
    ],
    [
      2,
      1,
      2,
      1
    ],
    [
      3,
      0,
      2,
      2
    ],
    [
      12,
      0,
      1,
      1
    ],
    [
      1,
      0,
      1,
      2,
      7,
      8,
      4
    ],
    [
      1,
      0,
      1,
      3,
      4,
      2,
      7,
      8,
      6
    ],
    [
      1,
      0,
      5,
      6,
      3,
      4,
      7,
      8,
      6
    ],
    [
      4,
      1,
      2,
      3,
      1
    ],
    [
      5,
      1,
      1
    ],
    [
      5,
      0,
      1,
      2,
      2
    ],
    [
      13,
      0,
      1,
      2,
      3
    ],
    [
      14,
      0,
      1,
      2,
      3
    ],
    [
      6,
      0,
      1,
      2,
      5,
      6,
      7,
      5
    ],
    [
      15,
      0,
      1,
      2,
      2
    ]
  ],
  [
    [
      [
        {
          "name": "img_notice_bg",
          "rect": [
            0,
            0,
            686,
            180
          ],
          "offset": [
            0,
            0
          ],
          "originalSize": [
            686,
            180
          ],
          "capInsets": [
            0,
            0,
            0,
            0
          ]
        }
      ],
      [
        7
      ],
      0,
      [
        0
      ],
      [
        2
      ],
      [
        1
      ]
    ],
    [
      [
        [
          8,
          "Page_Notice"
        ],
        [
          9,
          "Page_Notice",
          [
            -7,
            -8
          ],
          [
            [
              14,
              -5,
              -4,
              -3,
              -2
            ],
            [
              4,
              -6
            ]
          ],
          [
            15,
            -1,
            0
          ],
          [
            5,
            750,
            1334
          ]
        ],
        [
          10,
          "content",
          1,
          [
            -11,
            -12
          ],
          [
            [
              4,
              -9
            ],
            [
              16,
              2,
              -10
            ]
          ],
          [
            0,
            "f2NZOLJJxK/YN5/iASfR+j",
            1,
            0
          ],
          [
            4,
            4281479730
          ],
          [
            5,
            750,
            1334
          ]
        ],
        [
          13,
          "scrollview",
          2,
          [
            -16
          ],
          [
            [
              -13,
              [
                17,
                -14,
                [
                  9
                ]
              ],
              [
                5,
                4,
                -15
              ]
            ],
            1,
            4,
            4
          ],
          [
            0,
            "e63QdgGzNO74g+QDgZOS9i",
            1,
            0
          ],
          [
            5,
            750,
            1200
          ],
          [
            0,
            0.5,
            1
          ],
          [
            0,
            541.883,
            0,
            0,
            0,
            0,
            1,
            1,
            1,
            1
          ]
        ],
        [
          11,
          "layout",
          3,
          [
            -18
          ],
          [
            [
              18,
              1,
              2,
              50,
              -17,
              [
                5,
                750,
                255.68
              ]
            ]
          ],
          [
            0,
            "6aMhed0DpLKb9d8tabHVXx",
            1,
            0
          ],
          [
            5,
            750,
            255.68
          ],
          [
            0,
            0.5,
            1
          ]
        ],
        [
          1,
          "item",
          4,
          [
            -20,
            -21
          ],
          [
            [
              19,
              1,
              2,
              10,
              10,
              10,
              -19,
              [
                5,
                750,
                255.68
              ]
            ]
          ],
          [
            0,
            "87OcMlyQ9Or4RQUdBogT9k",
            1,
            0
          ],
          [
            5,
            750,
            255.68
          ],
          [
            0,
            -127.84,
            0,
            0,
            0,
            0,
            1,
            1,
            1,
            1
          ]
        ],
        [
          3,
          "shadow",
          1,
          [
            [
              6,
              0,
              -22,
              [
                0
              ],
              1
            ],
            [
              22,
              -23
            ],
            [
              5,
              3,
              -24
            ]
          ],
          [
            0,
            "53ldBS9XpDGqpySmMZZ+bN",
            1,
            0
          ],
          [
            4,
            4279111182
          ],
          [
            5,
            750,
            1334
          ]
        ],
        [
          1,
          "title",
          2,
          [
            -26,
            -27
          ],
          [
            [
              24,
              41,
              53.077999999999975,
              -25
            ]
          ],
          [
            0,
            "5dnc5B/gZHCLaVUMNJGa/t",
            1,
            0
          ],
          [
            5,
            750,
            0
          ],
          [
            0,
            613.922,
            0,
            0,
            0,
            0,
            1,
            1,
            1,
            1
          ]
        ],
        [
          12,
          "img_notice_bg",
          5,
          [
            -30
          ],
          [
            [
              6,
              0,
              -28,
              [
                7
              ],
              8
            ],
            [
              20,
              1,
              20,
              20,
              30,
              30,
              -29,
              [
                5,
                680,
                190.4
              ]
            ]
          ],
          [
            0,
            "0bfKlM6MBNybmC6q97KHXg",
            1,
            0
          ],
          [
            5,
            680,
            190.4
          ],
          [
            0,
            0.5,
            1.12
          ],
          [
            0,
            95.40800000000002,
            0,
            0,
            0,
            0,
            1,
            1,
            1,
            1
          ]
        ],
        [
          1,
          "btn_back",
          7,
          [
            -32
          ],
          [
            [
              23,
              3,
              -31,
              [
                [
                  25,
                  "3cb15XGsE5GQZggPIvrXbSn",
                  "Btn_Close_OnClick",
                  1
                ]
              ]
            ]
          ],
          [
            0,
            "12r8sUXJNP/ZlFpJY65Y4j",
            1,
            0
          ],
          [
            5,
            122,
            122
          ],
          [
            -320,
            0,
            0,
            0,
            0,
            0,
            1,
            1,
            1,
            0
          ]
        ],
        [
          2,
          "btn_back",
          9,
          [
            [
              21,
              -33,
              [
                2
              ],
              3
            ]
          ],
          [
            0,
            "begG6cKrJL8LJbZZBmvh84",
            1,
            0
          ],
          [
            5,
            24,
            42
          ],
          [
            0,
            0,
            0,
            0,
            0,
            0,
            1,
            1,
            1,
            0
          ]
        ],
        [
          3,
          "label_title",
          7,
          [
            [
              7,
              "系统通知",
              36,
              36,
              1,
              1,
              -34,
              [
                4
              ]
            ]
          ],
          [
            0,
            "bfeWxlHcNBQYbQb9mvNSeL",
            1,
            0
          ],
          [
            4,
            4282882528
          ],
          [
            5,
            144,
            45.36
          ]
        ],
        [
          2,
          "label_time",
          5,
          [
            [
              7,
              "2022-02-02 02:22",
              28,
              28,
              1,
              1,
              -35,
              [
                5
              ]
            ]
          ],
          [
            0,
            "0cyEvDlhdFxoXWdy0MOeT6",
            1,
            0
          ],
          [
            5,
            221.07,
            35.28
          ],
          [
            0,
            100.2,
            0,
            0,
            0,
            0,
            1,
            1,
            1,
            1
          ]
        ],
        [
          2,
          "label_notice",
          8,
          [
            [
              26,
              "您已成功注册为ZDPK的用户，我们将为您提供各大赛事的报名服务并可全程了解各地赛事的行程信息、直播内容、相关新闻，快去前往体验吧！",
              24,
              1,
              3,
              -36,
              [
                6
              ]
            ]
          ],
          [
            0,
            "0cGLoaRh9OKZhq5t0WmzEy",
            1,
            0
          ],
          [
            5,
            640,
            130.39999999999998
          ],
          [
            0,
            -117.12,
            0,
            0,
            0,
            0,
            1,
            1,
            1,
            1
          ]
        ],
        [
          27,
          false,
          3,
          4
        ]
      ],
      0,
      [
        0,
        3,
        1,
        0,
        4,
        5,
        0,
        5,
        4,
        0,
        6,
        14,
        0,
        0,
        1,
        0,
        0,
        1,
        0,
        -1,
        6,
        0,
        -2,
        2,
        0,
        0,
        2,
        0,
        0,
        2,
        0,
        -1,
        7,
        0,
        -2,
        3,
        0,
        -1,
        14,
        0,
        0,
        3,
        0,
        0,
        3,
        0,
        -1,
        4,
        0,
        0,
        4,
        0,
        -1,
        5,
        0,
        0,
        5,
        0,
        -1,
        12,
        0,
        -2,
        8,
        0,
        0,
        6,
        0,
        0,
        6,
        0,
        0,
        6,
        0,
        0,
        7,
        0,
        -1,
        9,
        0,
        -2,
        11,
        0,
        0,
        8,
        0,
        0,
        8,
        0,
        -1,
        13,
        0,
        0,
        9,
        0,
        -1,
        10,
        0,
        0,
        10,
        0,
        0,
        11,
        0,
        0,
        12,
        0,
        0,
        13,
        0,
        7,
        1,
        36
      ],
      [
        0,
        0,
        0,
        0,
        0,
        0,
        0,
        0,
        0,
        0
      ],
      [
        -1,
        1,
        -1,
        1,
        -1,
        -1,
        -1,
        -1,
        1,
        -1
      ],
      [
        0,
        2,
        0,
        3,
        0,
        0,
        0,
        0,
        4,
        0
      ]
    ]
  ]
]